yantra_patterns/__init__.py
yantra_patterns/protactive.py
yantra_patterns/fonts/eng.ttf
yantra_patterns/fonts/lklug.ttf
yantra_patterns-1.0.2.dist-info/METADATA
yantra_patterns-1.0.2.dist-info/WHEEL
yantra_patterns-1.0.2.dist-info/top_level.txt
yantra_patterns-1.0.2.dist-info/RECORD
