Metadata-Version: 2.2
Name: yantra_patterns
Version: 1.0.2
Summary: A package to generate yantras with Sinhala and English text.
Home-page: https://github.com/ishanoshada/yantra-patterns
Author: Ishan Oshada
Author-email: ishan.kodithuwakku.offical@gmail.com
Classifier: Programming Language :: Python :: 3
Classifier: License :: OSI Approved :: MIT License
Classifier: Operating System :: OS Independent
Requires-Dist: Pillow
Requires-Dist: numpy
Dynamic: author
Dynamic: author-email
Dynamic: classifier
Dynamic: description
Dynamic: description-content-type
Dynamic: home-page
Dynamic: requires-dist
Dynamic: summary
